[
  {
    "Favorite": true,
    "Viewed": null,
    "Adult": false,
    "OriginalTitle": "Orphan: First Kill",
    "ReleaseDate": "2022-07-27T00:00:00",
    "Title": "Orphan: First Kill",
    "Video": false,
    "BackdropPath": "/5GA3vV1aWWHTSDO5eno8V5zDo8r.jpg",
    "GenreIds": null,
    "OriginalLanguage": "en",
    "Overview": "After escaping from an Estonian psychiatric facility, Leena Klammer travels to America by impersonating Esther, the missing daughter of a wealthy family. But when her mask starts to slip, she is put against a mother who will protect her family from the murderous \u201Cchild\u201D at any cost.",
    "PosterPath": "/wSqAXL1EHVJ3MOnJzMhUngc8gFs.jpg",
    "VoteAverage": 6.966,
    "VoteCount": 763,
    "Id": 760161,
    "MediaType": 1,
    "Popularity": 6491.393
  },
  {
    "Favorite": true,
    "Viewed": null,
    "Adult": false,
    "OriginalTitle": "U-571",
    "ReleaseDate": "2000-04-20T00:00:00",
    "Title": "U-571",
    "Video": false,
    "BackdropPath": "/2W1AA5qZXJrR7MJXUgqj49JsLYy.jpg",
    "GenreIds": null,
    "OriginalLanguage": "en",
    "Overview": "In the midst of World War II, the battle under the sea rages and the Nazis have the upper hand as the Allies are unable to crack their war codes. However, after a wrecked U-boat sends out an SOS signal, the Allies realise this is their chance to seize the \u0027enigma coding machine\u0027.",
    "PosterPath": "/yeUhRSrlFcXhsuUai2ozWH6rNnK.jpg",
    "VoteAverage": 6.446,
    "VoteCount": 974,
    "Id": 3536,
    "MediaType": 1,
    "Popularity": 19.564
  }
]